exiul/__init__.py
exiul/files.py
exiul-0.0.3.dist-info/LICENSE
exiul-0.0.3.dist-info/METADATA
exiul-0.0.3.dist-info/WHEEL
exiul-0.0.3.dist-info/top_level.txt
exiul-0.0.3.dist-info/RECORD
