Metadata-Version: 2.1
Name: exiul
Version: 0.0.3
Summary: Some of my tools
Author-email: XiaoY <exidot@outlook.com>
Project-URL: Homepage, https://github.com/xinfor/exiul
Project-URL: Issues, https://github.com/xinfor/exiul/issues
Classifier: Programming Language :: Python :: 3
Classifier: License :: OSI Approved :: MIT License
Classifier: Operating System :: OS Independent
Requires-Python: >=3.8
License-File: LICENSE
